{
  "$defs": {
    "unitycatalog.tables.v1.GetTableExistsResponse.jsonschema.json": {
      "$schema": "https://json-schema.org/draft/2020-12/schema",
      "additionalProperties": false,
      "patternProperties": {
        "^(table_exists)$": {
          "default": false,
          "description": "Boolean reflecting if table exists.",
          "type": "boolean"
        }
      },
      "properties": {
        "tableExists": {
          "default": false,
          "description": "Boolean reflecting if table exists.",
          "type": "boolean"
        }
      },
      "title": "Get Table Exists Response",
      "type": "object"
    }
  },
  "$id": "unitycatalog.tables.v1.GetTableExistsResponse.jsonschema.bundle.json",
  "$ref": "#/$defs/unitycatalog.tables.v1.GetTableExistsResponse.jsonschema.json",
  "$schema": "https://json-schema.org/draft/2020-12/schema"
}
