{
  "db_name": "SQLite",
  "query": "\n            INSERT INTO objects ( id, label, name, namespace, properties, created_at )\n            VALUES ( ?, ?, ?, ?, ?, ? )\n            RETURNING\n                id AS \"id!\",\n                label AS \"label!\",\n                name AS \"name!\",\n                properties,\n                created_at AS \"created_at!\",\n                updated_at\n            ",
  "describe": {
    "columns": [
      {
        "name": "id!",
        "ordinal": 0,
        "type_info": "Blob"
      },
      {
        "name": "label!",
        "ordinal": 1,
        "type_info": "Text"
      },
      {
        "name": "name!",
        "ordinal": 2,
        "type_info": "Text"
      },
      {
        "name": "properties",
        "ordinal": 3,
        "type_info": "Text"
      },
      {
        "name": "created_at!",
        "ordinal": 4,
        "type_info": "Integer"
      },
      {
        "name": "updated_at",
        "ordinal": 5,
        "type_info": "Integer"
      }
    ],
    "parameters": {
      "Right": 6
    },
    "nullable": [
      false,
      false,
      false,
      true,
      false,
      true
    ]
  },
  "hash": "ac74f6d0735308334c40040b5d4d4b4105ad045e03223d5a8f8697a662a5fe51"
}
